MANIFEST.in
README.rst
setup.py
ChernMachine/ChernDaemon.py
ChernMachine/ChernDatabase.py
ChernMachine/__init__.py
ChernMachine/feeder.py
ChernMachine/main.py
ChernMachine/register.py
ChernMachine/runner.py
ChernMachine/server.py
ChernMachine/status.py
ChernMachine/kernel/VContainer.py
ChernMachine/kernel/VImage.py
ChernMachine/kernel/VJob.py
ChernMachine/kernel/__init__.py
Chern_Machine.egg-info/PKG-INFO
Chern_Machine.egg-info/SOURCES.txt
Chern_Machine.egg-info/dependency_links.txt
Chern_Machine.egg-info/entry_points.txt
Chern_Machine.egg-info/not-zip-safe
Chern_Machine.egg-info/requires.txt
Chern_Machine.egg-info/top_level.txt